traia_tools/__init__.py
traia_tools/index/__init__.py
traia_tools/index/index_retriever.py
traia_tools/index/traia_tools_index.json
traia_tools/tools/__init__.py
traia_tools/tools/coingecko_quote_tool/coingecko_quote_tool.py
traia_tools/tools/deepseek_safe_llm/__init__.py
traia_tools/tools/deepseek_safe_llm/deepseek_safe_llm.py
traia_tools/tools/file_read_tool/file_read_tool.py
traia_tools/tools/iatp_search_tool/iatp_search_tool.py
traia_tools/tools/json_search_tool/json_search_tool.py
traia_tools/tools/rag_tool/rag_tool.py
traia_tools/tools/s3_reader_tool/s3_reader_tool.py
traia_tools/tools/s3_writer_tool/s3_writer_tool.py
traia_tools/tools/scrape_website_tool/scrape_website_tool.py
traia_tools/tools/serper_dev_tool/serper_dev_tool.py
traia_tools/tools/serply_news_search_tool/serply_news_search_tool.py
traia_tools-0.1.36.dist-info/licenses/LICENSE
traia_tools-0.1.36.dist-info/METADATA
traia_tools-0.1.36.dist-info/WHEEL
traia_tools-0.1.36.dist-info/top_level.txt
traia_tools-0.1.36.dist-info/RECORD
