Metadata-Version: 2.4
Name: traia-tools
Version: 0.1.36
Summary: Custom tools for Traia/CrewAI for Web3 and crypto trading strategies
Project-URL: Documentation, https://docs.crewai.com/
Project-URL: Source, https://github.com/traia/traia-tools
Keywords: crewai,web3,cryptocurrency,tools
Classifier: Programming Language :: Python :: 3
Classifier: Operating System :: OS Independent
Requires-Python: >=3.12
License-File: LICENSE
Requires-Dist: beautifulsoup4>=4.14.2
Requires-Dist: boto3>=1.40.54
Requires-Dist: crewai==0.203.1
Requires-Dist: pydantic>=2.12.2
Requires-Dist: requests>=2.32.5
Requires-Dist: traia-iatp>=0.1.17
Provides-Extra: dev
Requires-Dist: twine>=5.0.0; extra == "dev"
Requires-Dist: build>=1.0.0; extra == "dev"
Requires-Dist: wheel; extra == "dev"
Dynamic: license-file
